docs/configuration.md
docs/install.md
docs/cookbook/clipboard.md
docs/guide/json.md
docs/guide/unsupported_params.md
docs/operations/filelist-to-md.md
paipe/__init__.py
paipe/cli.py
paipe/main.py
paipe/models.py
paipe/profiles.py
paipe/util.py
paipe/operations/__init__.py
paipe/operations/archive.py
paipe/operations/base.py
paipe/operations/subcli.py
paipe/operations/website.py
paipe/providers/__init__.py
paipe/providers/openai.py
paipe-0.1.17.dist-info/METADATA
paipe-0.1.17.dist-info/WHEEL
paipe-0.1.17.dist-info/entry_points.txt
paipe-0.1.17.dist-info/licenses/LICENSE
paipe-0.1.17.dist-info/RECORD
