Metadata-Version: 2.4
Name: paipe
Version: 0.1.17
Summary: A CLI tool for accessing the LLM API in the terminal.
Project-URL: homepage, https://github.com/socrateslee/paipe
License-File: LICENSE
Classifier: Environment :: Console
Classifier: Framework :: Pydantic
Classifier: Intended Audience :: Developers
Classifier: Intended Audience :: System Administrators
Classifier: License :: OSI Approved :: MIT License
Classifier: Programming Language :: Python
Classifier: Topic :: Scientific/Engineering :: Artificial Intelligence
Classifier: Topic :: System :: Shells
Requires-Python: >=3.10
Requires-Dist: dydantic
Requires-Dist: pydantic-ai-slim
Requires-Dist: pyyaml
Provides-Extra: all
Requires-Dist: pydantic-ai; extra == 'all'
Provides-Extra: cohere
Requires-Dist: pydantic-ai-slim[cohere]; extra == 'cohere'
Provides-Extra: groq
Requires-Dist: pydantic-ai-slim[groq]; extra == 'groq'
Provides-Extra: mistral
Requires-Dist: pydantic-ai-slim[mistral]; extra == 'mistral'
Provides-Extra: openai
Requires-Dist: pydantic-ai-slim[openai]; extra == 'openai'
